rawhttpy/__init__.py
rawhttpy/main.py
rawhttpy/rawhttpy-cli.py
rawhttpy/rawhttpy_cli.py
rawhttpy-0.1.dist-info/LICENSE
rawhttpy-0.1.dist-info/METADATA
rawhttpy-0.1.dist-info/WHEEL
rawhttpy-0.1.dist-info/entry_points.txt
rawhttpy-0.1.dist-info/top_level.txt
rawhttpy-0.1.dist-info/RECORD
