Metadata-Version: 2.1
Name: rawhttpy
Version: 0.1
Home-page: https://github.com/0xyy66/RawHTTPy
License-File: LICENSE
